keras_core/__init__.py
keras_core/_tf_keras/__init__.py
keras_core/_tf_keras/activations/__init__.py
keras_core/_tf_keras/applications/__init__.py
keras_core/_tf_keras/applications/convnext/__init__.py
keras_core/_tf_keras/applications/densenet/__init__.py
keras_core/_tf_keras/applications/efficientnet/__init__.py
keras_core/_tf_keras/applications/efficientnet_v2/__init__.py
keras_core/_tf_keras/applications/imagenet_utils/__init__.py
keras_core/_tf_keras/applications/inception_resnet_v2/__init__.py
keras_core/_tf_keras/applications/inception_v3/__init__.py
keras_core/_tf_keras/applications/mobilenet/__init__.py
keras_core/_tf_keras/applications/mobilenet_v2/__init__.py
keras_core/_tf_keras/applications/mobilenet_v3/__init__.py
keras_core/_tf_keras/applications/nasnet/__init__.py
keras_core/_tf_keras/applications/resnet/__init__.py
keras_core/_tf_keras/applications/resnet50/__init__.py
keras_core/_tf_keras/applications/resnet_v2/__init__.py
keras_core/_tf_keras/applications/vgg16/__init__.py
keras_core/_tf_keras/applications/vgg19/__init__.py
keras_core/_tf_keras/applications/xception/__init__.py
keras_core/_tf_keras/backend/__init__.py
keras_core/_tf_keras/callbacks/__init__.py
keras_core/_tf_keras/config/__init__.py
keras_core/_tf_keras/constraints/__init__.py
keras_core/_tf_keras/datasets/__init__.py
keras_core/_tf_keras/datasets/boston_housing/__init__.py
keras_core/_tf_keras/datasets/cifar10/__init__.py
keras_core/_tf_keras/datasets/cifar100/__init__.py
keras_core/_tf_keras/datasets/fashion_mnist/__init__.py
keras_core/_tf_keras/datasets/imdb/__init__.py
keras_core/_tf_keras/datasets/mnist/__init__.py
keras_core/_tf_keras/datasets/reuters/__init__.py
keras_core/_tf_keras/distribution/__init__.py
keras_core/_tf_keras/export/__init__.py
keras_core/_tf_keras/initializers/__init__.py
keras_core/_tf_keras/layers/__init__.py
keras_core/_tf_keras/legacy/__init__.py
keras_core/_tf_keras/legacy/saving/__init__.py
keras_core/_tf_keras/losses/__init__.py
keras_core-0.1.6.dist-info/METADATA
keras_core-0.1.6.dist-info/WHEEL
keras_core-0.1.6.dist-info/top_level.txt
keras_core-0.1.6.dist-info/RECORD
