Metadata-Version: 2.1
Name: keras-core
Version: 0.1.6
Summary: Multi-backend Keras.
Home-page: https://github.com/keras-team/keras-core
Author: Keras team
Author-email: keras-users@googlegroups.com
License: Apache License 2.0
Classifier: Development Status :: 4 - Beta
Classifier: Programming Language :: Python :: 3
Classifier: Programming Language :: Python :: 3.9
Classifier: Programming Language :: Python :: 3.10
Classifier: Programming Language :: Python :: 3.11
Classifier: Programming Language :: Python :: 3 :: Only
Classifier: Operating System :: Unix
Classifier: Operating System :: MacOS
Classifier: Intended Audience :: Science/Research
Classifier: Topic :: Scientific/Engineering
Classifier: Topic :: Software Development
Requires-Python: >=3.9
Requires-Dist: absl-py
Requires-Dist: numpy
Requires-Dist: rich
Requires-Dist: namex
Requires-Dist: h5py
Requires-Dist: dm-tree
